{
  "metainfo" : {
    "id" : "1",
    "language" : "python",
    "fabricId" : "299",
    "frontEndLanguage" : "sql",
    "mode" : "batch",
    "udfs" : {
      "language" : "python",
      "udfs" : [ ]
    },
    "udafs" : {
      "language" : "python",
      "code" : ""
    },
    "configuration" : {
      "common" : {
        "type" : "record",
        "fields" : [ ]
      },
      "fabrics" : { },
      "instances" : { },
      "selected" : "default"
    },
    "sparkConf" : [ ],
    "hadoopConf" : [ ],
    "codeMode" : "sparse",
    "buildSystem" : "maven",
    "externalDependencies" : [ ],
    "isImported" : false,
    "interimMode" : "Full",
    "interimModeEnabled" : true,
    "visualCodeInterimMode" : "Disabled",
    "recordsLimit" : {
      "enabled" : false,
      "value" : 1000
    },
    "topLevelPackage" : "workflowautomatedpull_origin11663851592503"
  },
  "connections" : [ ],
  "processes" : {
    "6R6Y_jeMj6695E9x1sPUQ$$zdlb6HGpd0nkcEuyP4EBB" : {
      "id" : "6R6Y_jeMj6695E9x1sPUQ$$zdlb6HGpd0nkcEuyP4EBB",
      "component" : "Script",
      "metadata" : {
        "label" : "Script_0",
        "slug" : "Script_0",
        "x" : 140,
        "y" : 160,
        "phase" : 0,
        "cache" : false,
        "detailedStats" : false,
        "isImported" : false
      },
      "ports" : {
        "inputs" : [ {
          "id" : "36bcYCsoOj7asowFRe2MB$$RrQ9ijmzFa0QirlDzrBT4",
          "slug" : "in0"
        } ],
        "outputs" : [ {
          "id" : "Xh7WBXTgErPCRdCnrUYlI$$uF7LFkipbeShExcuaN1b_",
          "slug" : "out0"
        } ],
        "selectedInputFields" : [ ],
        "isCustomOutputSchema" : false
      },
      "properties" : {
        "script" : "",
        "scriptMethodHeader" : "def Script(spark: SparkSession, in: DataFrame) -> Script:",
        "scriptMethodFooter" : "    return out0"
      }
    }
  },
  "ports" : {
    "inputs" : [ ],
    "outputs" : [ ],
    "selectedInputFields" : [ ],
    "isCustomOutputSchema" : false
  }
}